LICENSE.txt
MANIFEST.in
README.md
VERSION.txt
requirements.txt
setup.cfg
setup.py
myotest/__init__.py
myotest/client.py
myotest/exception.py
myotest/models.py
myotest/requests.py
myotest/version.py
myotest/wrapper.py
revo_client.egg-info/PKG-INFO
revo_client.egg-info/SOURCES.txt
revo_client.egg-info/dependency_links.txt
revo_client.egg-info/not-zip-safe
revo_client.egg-info/requires.txt
revo_client.egg-info/top_level.txt
tests/__init__.py
tests/test_client.py