Metadata-Version: 1.2
Name: revo-client
Version: 0.9.0
Summary: Python client for Myotest smart coaching API
Home-page: https://github.com/Myotest/python-revo-client
Author: myotest SA
Author-email: dev@myotest.com
License: MIT
Platform: UNKNOWN
Classifier: Development Status :: 3 - Alpha
Classifier: Environment :: Console
Classifier: Intended Audience :: Developers
Classifier: License :: OSI Approved :: MIT License
Classifier: Operating System :: OS Independent
Classifier: Topic :: Software Development :: Libraries :: Pike Modules
Classifier: Programming Language :: Python :: 3
Classifier: Programming Language :: Python :: 3.4
Classifier: Programming Language :: Python :: 3.5
Classifier: Programming Language :: Python :: 3.6
Requires-Python: >=3
